odoo/addons/sale_delivery_carrier_preference/README.rst
odoo/addons/sale_delivery_carrier_preference/__init__.py
odoo/addons/sale_delivery_carrier_preference/__manifest__.py
odoo/addons/sale_delivery_carrier_preference/i18n/sale_delivery_carrier_preference.pot
odoo/addons/sale_delivery_carrier_preference/models/__init__.py
odoo/addons/sale_delivery_carrier_preference/models/delivery_carrier_preference.py
odoo/addons/sale_delivery_carrier_preference/models/sale_order.py
odoo/addons/sale_delivery_carrier_preference/readme/CONFIGURE.rst
odoo/addons/sale_delivery_carrier_preference/readme/CONTRIBUTORS.rst
odoo/addons/sale_delivery_carrier_preference/readme/DESCRIPTION.rst
odoo/addons/sale_delivery_carrier_preference/readme/ROADMAP.rst
odoo/addons/sale_delivery_carrier_preference/security/ir.model.access.csv
odoo/addons/sale_delivery_carrier_preference/static/description/icon.png
odoo/addons/sale_delivery_carrier_preference/static/description/index.html
odoo/addons/sale_delivery_carrier_preference/tests/__init__.py
odoo/addons/sale_delivery_carrier_preference/tests/test_delivery_carrier_preference.py
odoo/addons/sale_delivery_carrier_preference/views/delivery_carrier_preference.xml
odoo13_addon_sale_delivery_carrier_preference-13.0.1.2.0.dist-info/METADATA
odoo13_addon_sale_delivery_carrier_preference-13.0.1.2.0.dist-info/WHEEL
odoo13_addon_sale_delivery_carrier_preference-13.0.1.2.0.dist-info/top_level.txt
odoo13_addon_sale_delivery_carrier_preference-13.0.1.2.0.dist-info/RECORD
